pyexcel_cli/__init__.py
pyexcel_cli/_shared.py
pyexcel_cli/diff.py
pyexcel_cli/main.py
pyexcel_cli/merge.py
pyexcel_cli/split.py
pyexcel_cli/transcode.py
pyexcel_cli/view.py
pyexcel_cli-0.0.3.dist-info/DESCRIPTION.rst
pyexcel_cli-0.0.3.dist-info/METADATA
pyexcel_cli-0.0.3.dist-info/RECORD
pyexcel_cli-0.0.3.dist-info/WHEEL
pyexcel_cli-0.0.3.dist-info/entry_points.txt
pyexcel_cli-0.0.3.dist-info/metadata.json
pyexcel_cli-0.0.3.dist-info/top_level.txt
