Metadata-Version: 2.0
Name: pyexcel-cli
Version: 0.0.3
Summary: A command utility to read and write data in csv, tsv, xls, xlsx and ods format.
Home-page: UNKNOWN
Author: C.W.
Author-email: wangc_2011@hotmail.com
License: New BSD
Keywords: excel,python,pyexcel
Platform: UNKNOWN
Classifier: Topic :: Office/Business
Classifier: Topic :: Utilities
Classifier: Topic :: Software Development :: Libraries
Classifier: Programming Language :: Python
Classifier: License :: OSI Approved :: BSD License
Classifier: Intended Audience :: Developers
Classifier: Programming Language :: Python :: 2.6
Classifier: Programming Language :: Python :: 2.7
Classifier: Programming Language :: Python :: 3.3
Classifier: Programming Language :: Python :: 3.4
Classifier: Programming Language :: Python :: 3.5
Classifier: Programming Language :: Python :: 3.6
Requires-Dist: pyexcel (>=0.5.0)
Requires-Dist: pyexcel-io (>=0.4.0)
Requires-Dist: Click (>=5.0)
